LICENSE
MANIFEST.in
README.rst
setup.cfg
setup.py
versioneer.py
artellapipe/__init__.py
artellapipe/tools/__init__.py
artellapipe/tools/tagger/__init__.py
artellapipe/tools/tagger/__logging__.ini
artellapipe/tools/tagger/__version__.py
artellapipe/tools/tagger/_version.py
artellapipe/tools/tagger/core/__init__.py
artellapipe/tools/tagger/core/tagger.py
artellapipe/tools/tagger/editors/__init__.py
artellapipe/tools/tagger/editors/descriptioneditor.py
artellapipe/tools/tagger/editors/nameeditor.py
artellapipe/tools/tagger/editors/typeeditor.py
artellapipe/tools/tagger/resources/images/tagger_logo.png
artellapipe/tools/tagger/widgets/__init__.py
artellapipe/tools/tagger/widgets/tagger.py
artellapipe/tools/tagger/widgets/taggereditor.py
artellapipe/tools/tagger/widgets/taggerinfo.py
artellapipe_tools_tagger.egg-info/PKG-INFO
artellapipe_tools_tagger.egg-info/SOURCES.txt
artellapipe_tools_tagger.egg-info/dependency_links.txt
artellapipe_tools_tagger.egg-info/not-zip-safe
artellapipe_tools_tagger.egg-info/requires.txt
artellapipe_tools_tagger.egg-info/top_level.txt
tests/__init__.py
tests/test_general.py