Metadata-Version: 2.1
Name: artellapipe-tools-tagger
Version: 0.0.5
Summary: Tool to manage tag information
Home-page: https://github.com/ArtellaPipe/artellapipe-tools-tagger
Author: Tomas Poveda
Author-email: tpovedatd@gmail.com
License: MIT
Platform: UNKNOWN
Provides-Extra: dev
Provides-Extra: test
